tagwrapper/VERSION
tagwrapper/__init__.py
tagwrapper/common.py
tagwrapper/flac.py
tagwrapper/monkeysaudio.py
tagwrapper/mp3.py
tagwrapper/mp4.py
tagwrapper/ogg.py
tagwrapper/trueaudio.py
tagwrapper/util.py
tagwrapper/wave.py
MutagenTagWrapper-0.2.0.dist-info/LICENSE
MutagenTagWrapper-0.2.0.dist-info/METADATA
MutagenTagWrapper-0.2.0.dist-info/WHEEL
MutagenTagWrapper-0.2.0.dist-info/top_level.txt
MutagenTagWrapper-0.2.0.dist-info/RECORD
