Metadata-Version: 2.1
Name: MutagenTagWrapper
Version: 0.2.0
Summary: 为各种多媒体标签格式提供统一的编辑接口
Home-page: https://github.com/nukemiko/MutagenTagWrapper
License: MIT
Project-URL: Documentation, https://github.com/nukemiko/MutagenTagWrapper
Project-URL: Source, https://github.com/nukemiko/MutagenTagWrapper
Project-URL: Releases, https://github.com/nukemiko/MutagenTagWrapper/releases
Project-URL: Issues, https://github.com/nukemiko/MutagenTagWrapper/issues
Platform: Any
Classifier: License :: OSI Approved :: MIT License
Classifier: Topic :: Multimedia :: Sound/Audio
Classifier: Programming Language :: Python :: 3.8
Classifier: Programming Language :: Python :: 3.9
Classifier: Programming Language :: Python :: 3.10
Requires-Python: >=3.8
License-File: LICENSE
Requires-Dist: mutagen
